use_case_outcome/__init__.py
use_case_outcome-1.2.1.dist-info/METADATA
use_case_outcome-1.2.1.dist-info/WHEEL
use_case_outcome-1.2.1.dist-info/RECORD
