Metadata-Version: 2.1
Name: use-case-outcome
Version: 1.2.1
Summary: Package for collecting information about the execution of a use case
Author: Ross Bown
Author-email: rossbo@softcat.com
Requires-Python: >=3.7,<4.0
Classifier: Programming Language :: Python :: 3
Classifier: Programming Language :: Python :: 3.7
Classifier: Programming Language :: Python :: 3.8
Classifier: Programming Language :: Python :: 3.9
Classifier: Programming Language :: Python :: 3.10
Classifier: Programming Language :: Python :: 3.11
Requires-Dist: swimlane (>=10.9.1,<11.0.0)
